CHANGES.txt
README.txt
buildout.cfg
setup.cfg
setup.py
hostout/__init__.py
hostout.centos.egg-info/PKG-INFO
hostout.centos.egg-info/SOURCES.txt
hostout.centos.egg-info/dependency_links.txt
hostout.centos.egg-info/entry_points.txt
hostout.centos.egg-info/namespace_packages.txt
hostout.centos.egg-info/not-zip-safe
hostout.centos.egg-info/requires.txt
hostout.centos.egg-info/top_level.txt
hostout/centos/README.txt
hostout/centos/__init__.py
hostout/centos/fabfile.py
hostout/centos/tests.py